[{"date":"2025-03-21","open":52,"high":52,"low":50.7,"close":51.9,"volume":10195495},{"date":"2025-03-24","open":51.5,"high":51.6,"low":50.1,"close":50.1,"volume":10239871},{"date":"2025-03-25","open":50.6,"high":50.7,"low":49.85,"close":50.5,"volume":7759225},{"date":"2025-03-26","open":50.5,"high":51.5,"low":50.2,"close":51.5,"volume":5942001},{"date":"2025-03-27","open":51.1,"high":51.4,"low":50.4,"close":51,"volume":4947527},{"date":"2025-03-28","open":50.5,"high":50.8,"low":49.75,"close":50.1,"volume":4734028},{"date":"2025-03-31","open":49,"high":49.95,"low":48.9,"close":49,"volume":6115580},{"date":"2025-04-01","open":49.8,"high":49.9,"low":49.1,"close":49.6,"volume":2851141},{"date":"2025-04-02","open":49.95,"high":50.6,"low":49.3,"close":49.5,"volume":3131124},{"date":"2025-04-07","open":44.55,"high":44.55,"low":44.55,"close":44.55,"volume":614575},{"date":"2025-04-08","open":42,"high":45.5,"low":41.9,"close":45.1,"volume":9232065},{"date":"2025-04-09","open":44.5,"high":47.6,"low":44.5,"close":45.85,"volume":12423567},{"date":"2025-04-10","open":49.75,"high":50.4,"low":48.2,"close":50.2,"volume":6297402},{"date":"2025-04-11","open":49,"high":50.8,"low":48.95,"close":49.75,"volume":6623887},{"date":"2025-04-14","open":49.4,"high":50.1,"low":48.8,"close":48.8,"volume":4542237},{"date":"2025-04-15","open":48.95,"high":49.75,"low":48.7,"close":49.2,"volume":3268819},{"date":"2025-04-16","open":48.9,"high":50.4,"low":48.9,"close":48.9,"volume":4513121},{"date":"2025-04-17","open":49.6,"high":50.3,"low":49.05,"close":49.9,"volume":5743416},{"date":"2025-04-18","open":50.3,"high":51.2,"low":49.1,"close":49.1,"volume":5375282},{"date":"2025-04-21","open":49.4,"high":49.7,"low":48,"close":48,"volume":2453064},{"date":"2025-04-22","open":47.6,"high":48.65,"low":47.5,"close":47.6,"volume":2660879},{"date":"2025-04-23","open":48.1,"high":48.9,"low":47.95,"close":47.95,"volume":1837389},{"date":"2025-04-24","open":48.25,"high":48.25,"low":47.2,"close":47.25,"volume":2652155},{"date":"2025-04-25","open":47.55,"high":47.75,"low":47.1,"close":47.1,"volume":2273740},{"date":"2025-04-28","open":47.15,"high":48.5,"low":47.15,"close":48.5,"volume":2760378},{"date":"2025-04-29","open":48.15,"high":49.45,"low":48,"close":49.2,"volume":3251426},{"date":"2025-04-30","open":49.1,"high":49.65,"low":48.85,"close":49.1,"volume":2745558},{"date":"2025-05-02","open":49.55,"high":51,"low":49.5,"close":50.8,"volume":4970909},{"date":"2025-05-05","open":50.8,"high":52.2,"low":50.7,"close":51.1,"volume":6352384},{"date":"2025-05-06","open":51.1,"high":52.1,"low":50.8,"close":51.4,"volume":2576840},{"date":"2025-05-07","open":51.4,"high":52,"low":51.4,"close":51.5,"volume":2420471},{"date":"2025-05-08","open":51.8,"high":52.1,"low":51.5,"close":51.5,"volume":3249335},{"date":"2025-05-09","open":51.5,"high":51.9,"low":51.2,"close":51.9,"volume":3298028},{"date":"2025-05-12","open":52.2,"high":52.5,"low":51.7,"close":52.1,"volume":2051090},{"date":"2025-05-13","open":51.8,"high":52.9,"low":51.8,"close":52.9,"volume":4041455},{"date":"2025-05-14","open":53.2,"high":53.3,"low":52.5,"close":52.6,"volume":3213821},{"date":"2025-05-15","open":52.4,"high":53.1,"low":52,"close":53.1,"volume":5791559},{"date":"2025-05-16","open":53.1,"high":53.5,"low":52.1,"close":52.3,"volume":5409493},{"date":"2025-05-19","open":52.1,"high":53,"low":51.8,"close":52.3,"volume":5249041},{"date":"2025-05-20","open":52.5,"high":52.7,"low":51.3,"close":51.5,"volume":4812996},{"date":"2025-05-21","open":51.7,"high":52.5,"low":51.1,"close":52.4,"volume":3473455},{"date":"2025-05-22","open":52.2,"high":53.2,"low":52.1,"close":52.9,"volume":3218613},{"date":"2025-05-23","open":52.9,"high":53.4,"low":52.9,"close":52.9,"volume":3288427},{"date":"2025-05-26","open":53.4,"high":53.4,"low":52.8,"close":52.9,"volume":2168114},{"date":"2025-05-27","open":53,"high":53.3,"low":52.2,"close":52.2,"volume":2637796},{"date":"2025-05-28","open":52.8,"high":52.9,"low":52,"close":52.2,"volume":1914777},{"date":"2025-05-29","open":52.2,"high":52.9,"low":52.2,"close":52.7,"volume":1822660},{"date":"2025-06-02","open":52,"high":52.9,"low":52,"close":52.7,"volume":2934012},{"date":"2025-06-03","open":52.1,"high":53.2,"low":52.1,"close":53.2,"volume":3676700},{"date":"2025-06-04","open":53.2,"high":53.4,"low":52.6,"close":52.6,"volume":4418361},{"date":"2025-06-05","open":52.6,"high":53.1,"low":51.4,"close":51.4,"volume":3448086},{"date":"2025-06-06","open":51.5,"high":52.4,"low":51.4,"close":52.2,"volume":1986231},{"date":"2025-06-09","open":52.2,"high":52.9,"low":52.1,"close":52.5,"volume":3211466},{"date":"2025-06-10","open":52.2,"high":52.9,"low":52,"close":52.4,"volume":3006069},{"date":"2025-06-11","open":52.4,"high":53.1,"low":52.3,"close":52.6,"volume":3843883},{"date":"2025-06-12","open":52.6,"high":53.2,"low":52.6,"close":52.8,"volume":2400843},{"date":"2025-06-13","open":52.3,"high":53.6,"low":52.3,"close":52.8,"volume":3578509},{"date":"2025-06-16","open":53,"high":53.4,"low":52.7,"close":53.4,"volume":3181616},{"date":"2025-06-17","open":53.6,"high":53.6,"low":52.6,"close":53.2,"volume":4914904},{"date":"2025-06-18","open":52.5,"high":52.8,"low":52.3,"close":52.6,"volume":4884723},{"date":"2025-06-19","open":50,"high":50.2,"low":48.75,"close":48.75,"volume":8627093},{"date":"2025-06-20","open":48.55,"high":48.9,"low":47.5,"close":48.4,"volume":8080974},{"date":"2025-06-23","open":47.9,"high":47.9,"low":46.65,"close":47,"volume":5858120},{"date":"2025-06-24","open":47.6,"high":47.85,"low":47.1,"close":47.85,"volume":5936751},{"date":"2025-06-25","open":47.9,"high":48.3,"low":47.4,"close":48.1,"volume":4583347},{"date":"2025-06-26","open":48.4,"high":49.5,"low":48.15,"close":49.1,"volume":4732562},{"date":"2025-06-27","open":49.4,"high":49.75,"low":48.85,"close":49.45,"volume":3079572},{"date":"2025-06-30","open":49.45,"high":49.45,"low":46.8,"close":47.3,"volume":17406836},{"date":"2025-07-01","open":47.7,"high":48.7,"low":47.3,"close":47.65,"volume":17204543},{"date":"2025-07-02","open":47.95,"high":49.1,"low":47.85,"close":48.95,"volume":3964982},{"date":"2025-07-03","open":48.8,"high":49.15,"low":48.7,"close":48.8,"volume":1813158},{"date":"2025-07-04","open":48.8,"high":48.8,"low":47.7,"close":47.95,"volume":2676925},{"date":"2025-07-07","open":47.7,"high":47.9,"low":47.35,"close":47.45,"volume":2811754},{"date":"2025-07-08","open":47.9,"high":47.95,"low":46.45,"close":46.45,"volume":3210178},{"date":"2025-07-09","open":46.35,"high":46.65,"low":46.1,"close":46.65,"volume":2299412},{"date":"2025-07-10","open":46.65,"high":46.7,"low":46.2,"close":46.55,"volume":3158603},{"date":"2025-07-11","open":46.25,"high":46.95,"low":46.25,"close":46.85,"volume":2469104},{"date":"2025-07-14","open":47.2,"high":48.3,"low":46.9,"close":47.25,"volume":5728623},{"date":"2025-07-15","open":47.1,"high":47.95,"low":47.1,"close":47.95,"volume":3027097},{"date":"2025-07-16","open":47.65,"high":48.25,"low":47.4,"close":47.55,"volume":3625941},{"date":"2025-07-17","open":47.75,"high":48.1,"low":47.55,"close":47.75,"volume":2034888},{"date":"2025-07-18","open":48.3,"high":48.3,"low":47.5,"close":47.8,"volume":2482905},{"date":"2025-07-21","open":48.65,"high":49.3,"low":48.2,"close":48.4,"volume":5925641},{"date":"2025-07-22","open":48.75,"high":48.75,"low":46.5,"close":46.6,"volume":7391164},{"date":"2025-07-23","open":47.15,"high":47.2,"low":46.1,"close":46.9,"volume":6953903},{"date":"2025-07-24","open":47,"high":47.05,"low":46.35,"close":46.85,"volume":5458279},{"date":"2025-07-25","open":46.7,"high":46.75,"low":46.2,"close":46.45,"volume":3915855},{"date":"2025-07-28","open":46.55,"high":46.75,"low":46.15,"close":46.25,"volume":3557505},{"date":"2025-07-29","open":46.25,"high":46.7,"low":46.2,"close":46.4,"volume":2741552},{"date":"2025-07-31","open":51,"high":51,"low":51,"close":51,"volume":5686853},{"date":"2025-08-04","open":56.1,"high":57.5,"low":54.1,"close":54.1,"volume":74845849},{"date":"2025-08-05","open":54.4,"high":54.8,"low":52.7,"close":52.9,"volume":31167960},{"date":"2025-08-06","open":53.2,"high":54.8,"low":53,"close":54.3,"volume":20417388},{"date":"2025-08-07","open":56,"high":59.2,"low":55.3,"close":56.2,"volume":73425046},{"date":"2025-08-08","open":56.3,"high":56.4,"low":55.1,"close":55.5,"volume":20263841},{"date":"2025-08-11","open":55.3,"high":55.8,"low":54.8,"close":55.3,"volume":10529532},{"date":"2025-08-12","open":55.6,"high":56.2,"low":54.5,"close":54.5,"volume":13360681},{"date":"2025-08-13","open":54.8,"high":55.6,"low":54,"close":54.7,"volume":12616918},{"date":"2025-08-14","open":55.1,"high":56.2,"low":54.8,"close":55.7,"volume":16651444},{"date":"2025-08-15","open":56,"high":56.3,"low":54.7,"close":55.5,"volume":23499020},{"date":"2025-08-18","open":55.2,"high":60.4,"low":55.1,"close":58.5,"volume":53022039},{"date":"2025-08-19","open":59.4,"high":59.4,"low":57.5,"close":57.8,"volume":19692436},{"date":"2025-08-20","open":57.6,"high":59,"low":56.1,"close":58,"volume":22552083},{"date":"2025-08-21","open":58.9,"high":63.8,"low":58.3,"close":63.8,"volume":58610690},{"date":"2025-08-22","open":67.2,"high":70.1,"low":66,"close":67.5,"volume":166957108},{"date":"2025-08-25","open":71.8,"high":74.2,"low":70,"close":74.2,"volume":131710874},{"date":"2025-08-26","open":75.1,"high":75.6,"low":68.9,"close":69.7,"volume":132982597},{"date":"2025-08-27","open":71.1,"high":72.5,"low":70,"close":70.5,"volume":65719443},{"date":"2025-08-28","open":70.3,"high":70.3,"low":68,"close":68.5,"volume":43710212},{"date":"2025-08-29","open":68.8,"high":69,"low":67.6,"close":68,"volume":25700945},{"date":"2025-09-01","open":67.7,"high":69.6,"low":66.9,"close":67.2,"volume":33967739},{"date":"2025-09-02","open":67.5,"high":67.8,"low":65.1,"close":66.5,"volume":22745235},{"date":"2025-09-03","open":66.7,"high":67.5,"low":66.1,"close":66.8,"volume":12547836},{"date":"2025-09-04","open":67.8,"high":68.9,"low":66.5,"close":66.7,"volume":29970099},{"date":"2025-09-05","open":68.2,"high":68.4,"low":67.1,"close":68,"volume":18097718},{"date":"2025-09-08","open":68.9,"high":72.5,"low":66.8,"close":72.4,"volume":64702166},{"date":"2025-09-09","open":73.2,"high":79.6,"low":72,"close":79.6,"volume":174553442},{"date":"2025-09-10","open":82.5,"high":87.5,"low":82.4,"close":87.5,"volume":89104090},{"date":"2025-09-11","open":90.4,"high":95.6,"low":88.2,"close":93.1,"volume":200484049},{"date":"2025-09-12","open":93.6,"high":93.6,"low":88.7,"close":89.4,"volume":77439172},{"date":"2025-09-15","open":89,"high":91.7,"low":87.6,"close":88.2,"volume":56574441},{"date":"2025-09-16","open":89.1,"high":89.1,"low":84.7,"close":87,"volume":46526120},{"date":"2025-09-17","open":86.8,"high":88.7,"low":86.2,"close":86.9,"volume":31991802},{"date":"2025-09-18","open":87.7,"high":87.8,"low":82.2,"close":83.1,"volume":44698037},{"date":"2025-09-19","open":82.5,"high":82.5,"low":80.3,"close":80.8,"volume":33852173},{"date":"2025-09-22","open":80.9,"high":86.2,"low":80.9,"close":85.5,"volume":52544082},{"date":"2025-09-23","open":88,"high":94,"low":87.8,"close":94,"volume":123843801},{"date":"2025-09-24","open":95.6,"high":103,"low":94.2,"close":101.5,"volume":330182993},{"date":"2025-09-25","open":102.5,"high":108,"low":97.3,"close":98.9,"volume":182875756},{"date":"2025-09-26","open":98.6,"high":101.5,"low":93.3,"close":94.6,"volume":83503723},{"date":"2025-09-30","open":96,"high":99.4,"low":94.6,"close":95.1,"volume":95614613},{"date":"2025-10-01","open":95.1,"high":104.5,"low":94.5,"close":104.5,"volume":75348414},{"date":"2025-10-02","open":108.5,"high":114.5,"low":107,"close":114.5,"volume":162297770},{"date":"2025-10-03","open":114.5,"high":115.5,"low":111,"close":113.5,"volume":133011972},{"date":"2025-10-07","open":116.5,"high":119.5,"low":112.5,"close":113,"volume":86385174},{"date":"2025-10-08","open":110.5,"high":112,"low":108,"close":110.5,"volume":35751773},{"date":"2025-10-09","open":113.5,"high":115,"low":108,"close":109.5,"volume":43835340},{"date":"2025-10-13","open":101,"high":112.5,"low":101,"close":112.5,"volume":46255632},{"date":"2025-10-14","open":115,"high":115,"low":103.5,"close":104,"volume":74714582},{"date":"2025-10-15","open":106,"high":109.5,"low":104.5,"close":108,"volume":42915351},{"date":"2025-10-16","open":108,"high":114.5,"low":108,"close":111,"volume":62961054},{"date":"2025-10-17","open":108.5,"high":113,"low":106.5,"close":109,"volume":43396900},{"date":"2025-10-20","open":114,"high":119.5,"low":113.5,"close":119.5,"volume":71611560},{"date":"2025-10-21","open":125,"high":127.5,"low":113,"close":113.5,"volume":161674831},{"date":"2025-10-22","open":112,"high":116.5,"low":110.5,"close":116.5,"volume":58103225},{"date":"2025-10-23","open":114.5,"high":116,"low":112,"close":114,"volume":28817127},{"date":"2025-10-27","open":117.5,"high":119,"low":114,"close":115,"volume":55000531},{"date":"2025-10-28","open":116.5,"high":116.5,"low":113,"close":116,"volume":32436194},{"date":"2025-10-29","open":117,"high":117.5,"low":113,"close":114.5,"volume":49229225},{"date":"2025-10-30","open":116,"high":118,"low":114.5,"close":116.5,"volume":47434216},{"date":"2025-10-31","open":117,"high":121.5,"low":114.5,"close":116.5,"volume":70241264},{"date":"2025-11-03","open":117,"high":118.5,"low":114,"close":115.5,"volume":36422130},{"date":"2025-11-04","open":116,"high":117.5,"low":112,"close":113.5,"volume":33237542},{"date":"2025-11-05","open":108.5,"high":112,"low":107,"close":111,"volume":44299500},{"date":"2025-11-06","open":115.5,"high":116,"low":112,"close":112.5,"volume":40760506},{"date":"2025-11-07","open":110.5,"high":112.5,"low":108,"close":109,"volume":27753531},{"date":"2025-11-10","open":108.5,"high":109,"low":103,"close":106,"volume":31773387},{"date":"2025-11-11","open":107,"high":107.5,"low":103.5,"close":104.5,"volume":19983441},{"date":"2025-11-12","open":104.5,"high":106,"low":103.5,"close":106,"volume":13019925},{"date":"2025-11-13","open":106.5,"high":113.5,"low":105.5,"close":110.5,"volume":45643901},{"date":"2025-11-14","open":104,"high":105,"low":99.5,"close":99.8,"volume":71470026},{"date":"2025-11-17","open":100,"high":101,"low":96.2,"close":96.6,"volume":40489164},{"date":"2025-11-18","open":96,"high":97.5,"low":93.8,"close":93.8,"volume":31787336},{"date":"2025-11-19","open":93.8,"high":94.4,"low":92,"close":93,"volume":29644813},{"date":"2025-11-20","open":96.9,"high":98.8,"low":94.5,"close":96.1,"volume":31764581},{"date":"2025-11-21","open":93.6,"high":95,"low":91.6,"close":92,"volume":32445387},{"date":"2025-11-24","open":93.8,"high":94,"low":91,"close":92.9,"volume":115077027},{"date":"2025-11-25","open":95,"high":95,"low":87.6,"close":88.5,"volume":51510894},{"date":"2025-11-26","open":88.9,"high":89.2,"low":86.7,"close":87.2,"volume":30348465},{"date":"2025-11-27","open":87.5,"high":88.7,"low":86.6,"close":88.6,"volume":17399458},{"date":"2025-11-28","open":89,"high":89,"low":87.1,"close":87.7,"volume":16098956},{"date":"2025-12-01","open":87.5,"high":87.5,"low":84.7,"close":85,"volume":16500582},{"date":"2025-12-02","open":85.2,"high":88.5,"low":84.8,"close":86.6,"volume":22267869},{"date":"2025-12-03","open":87.2,"high":88.8,"low":86.4,"close":87,"volume":13110379},{"date":"2025-12-04","open":87.8,"high":89.3,"low":87.6,"close":88.8,"volume":19775959},{"date":"2025-12-05","open":89.6,"high":89.6,"low":87.5,"close":88.7,"volume":10701576},{"date":"2025-12-08","open":88.2,"high":89.6,"low":87.8,"close":88.6,"volume":11231981},{"date":"2025-12-09","open":88.7,"high":88.7,"low":86.3,"close":86.6,"volume":15130548},{"date":"2025-12-10","open":86.9,"high":87.8,"low":85.8,"close":85.8,"volume":12059098},{"date":"2025-12-11","open":86.4,"high":86.7,"low":84.1,"close":85,"volume":13737419},{"date":"2025-12-12","open":85.6,"high":92,"low":85.5,"close":87.7,"volume":51206704},{"date":"2025-12-15","open":86.3,"high":86.5,"low":84.2,"close":84.2,"volume":18685534},{"date":"2025-12-16","open":83.5,"high":84.3,"low":81.8,"close":82.5,"volume":19095203},{"date":"2025-12-17","open":83,"high":83.2,"low":82,"close":82.6,"volume":10226473},{"date":"2025-12-18","open":81.8,"high":82.2,"low":81,"close":82,"volume":11760704},{"date":"2025-12-19","open":83.1,"high":84.2,"low":82.5,"close":84.2,"volume":31440939},{"date":"2025-12-22","open":85.2,"high":89.8,"low":85.2,"close":87.7,"volume":43759043},{"date":"2025-12-23","open":88.9,"high":88.9,"low":85.2,"close":85.3,"volume":30600575},{"date":"2025-12-24","open":86.8,"high":87.9,"low":85.7,"close":86.3,"volume":28135769},{"date":"2025-12-26","open":87.1,"high":87.1,"low":84.9,"close":86.5,"volume":26166059},{"date":"2025-12-29","open":87,"high":88.4,"low":86.8,"close":87.4,"volume":17545045},{"date":"2025-12-30","open":87.5,"high":87.5,"low":84.5,"close":84.9,"volume":16381762},{"date":"2025-12-31","open":85.1,"high":85.7,"low":84,"close":84,"volume":8706780},{"date":"2026-01-02","open":84,"high":85,"low":83.2,"close":84.3,"volume":9024901},{"date":"2026-01-05","open":84.3,"high":85.9,"low":83.2,"close":83.7,"volume":10745262},{"date":"2026-01-06","open":84,"high":84.4,"low":82.6,"close":83.5,"volume":12523632},{"date":"2026-01-07","open":83.1,"high":83.7,"low":82.5,"close":82.7,"volume":10751370},{"date":"2026-01-08","open":82.7,"high":82.9,"low":81.3,"close":81.6,"volume":11502958},{"date":"2026-01-09","open":82.9,"high":84,"low":82,"close":83.4,"volume":17564193},{"date":"2026-01-12","open":84,"high":84.5,"low":83.3,"close":83.6,"volume":9489996},{"date":"2026-01-13","open":84.2,"high":85.2,"low":82.3,"close":82.3,"volume":12274392},{"date":"2026-01-14","open":83.4,"high":90.5,"low":83.3,"close":90.5,"volume":60250930},{"date":"2026-01-15","open":92,"high":92,"low":85.2,"close":85.8,"volume":70865441},{"date":"2026-01-16","open":86.8,"high":89.4,"low":83.8,"close":88.9,"volume":60338765},{"date":"2026-01-19","open":90,"high":91.3,"low":85.7,"close":87.9,"volume":63866034},{"date":"2026-01-20","open":87.9,"high":90.5,"low":86.9,"close":88.8,"volume":52702360},{"date":"2026-01-21","open":88,"high":90.2,"low":86,"close":86,"volume":42059099},{"date":"2026-01-22","open":87.5,"high":92,"low":87.2,"close":89.3,"volume":62999948},{"date":"2026-01-23","open":91.7,"high":95,"low":89.3,"close":89.4,"volume":70153545},{"date":"2026-01-26","open":89.6,"high":89.7,"low":86.5,"close":87.2,"volume":28247474},{"date":"2026-01-27","open":87.2,"high":87.3,"low":84.7,"close":85.4,"volume":20840443},{"date":"2026-01-28","open":85.8,"high":88,"low":85.1,"close":87.7,"volume":19622921},{"date":"2026-01-29","open":88.4,"high":88.4,"low":84.5,"close":84.5,"volume":19765087},{"date":"2026-01-30","open":83.7,"high":83.9,"low":81.1,"close":81.8,"volume":26516811},{"date":"2026-02-02","open":80.5,"high":81.3,"low":78,"close":79.1,"volume":23064354},{"date":"2026-02-03","open":81.5,"high":83,"low":80.2,"close":81.7,"volume":12814595},{"date":"2026-02-04","open":81.7,"high":83.3,"low":81.1,"close":82.7,"volume":8552513},{"date":"2026-02-05","open":82.1,"high":82.2,"low":79.6,"close":79.8,"volume":8979068},{"date":"2026-02-06","open":80.8,"high":81.4,"low":79,"close":80,"volume":14711321},{"date":"2026-02-09","open":81.9,"high":82.9,"low":80.1,"close":80.1,"volume":11913760},{"date":"2026-02-10","open":80.4,"high":81.5,"low":79.2,"close":79.3,"volume":9689522},{"date":"2026-02-11","open":80.1,"high":80.1,"low":78.2,"close":79.8,"volume":8128441},{"date":"2026-02-23","open":80.1,"high":82.9,"low":79.1,"close":82,"volume":17522597},{"date":"2026-02-24","open":82.8,"high":82.8,"low":81.1,"close":81.7,"volume":9962051},{"date":"2026-02-25","open":81.8,"high":84.3,"low":81.6,"close":82.6,"volume":16971219},{"date":"2026-02-26","open":83.3,"high":83.3,"low":81,"close":82.9,"volume":24050802},{"date":"2026-03-02","open":80,"high":81.9,"low":79,"close":80.5,"volume":15139603},{"date":"2026-03-03","open":81.2,"high":81.2,"low":76.4,"close":76.5,"volume":21230011},{"date":"2026-03-04","open":73.4,"high":74.7,"low":70.5,"close":70.8,"volume":19853045},{"date":"2026-03-05","open":72.8,"high":73.7,"low":71.6,"close":73,"volume":10270321},{"date":"2026-03-06","open":71.6,"high":73.1,"low":71,"close":72.3,"volume":6890421},{"date":"2026-03-09","open":67.2,"high":69.1,"low":66.1,"close":68.8,"volume":11461999},{"date":"2026-03-10","open":71.1,"high":71.1,"low":69.1,"close":70,"volume":6009123},{"date":"2026-03-11","open":71.1,"high":72.2,"low":71,"close":71.6,"volume":5523929},{"date":"2026-03-12","open":71.6,"high":72.2,"low":70.3,"close":70.9,"volume":6778251},{"date":"2026-03-13","open":69.3,"high":70.8,"low":69.1,"close":69.9,"volume":7689544},{"date":"2026-03-16","open":70,"high":70.3,"low":68,"close":69.3,"volume":12549278},{"date":"2026-03-17","open":70,"high":71,"low":69.9,"close":70.3,"volume":7097053},{"date":"2026-03-18","open":71.5,"high":71.7,"low":70.6,"close":71.1,"volume":6802795},{"date":"2026-03-19","open":70.5,"high":70.5,"low":68.3,"close":68.3,"volume":9752370},{"date":"2026-03-20","open":68.4,"high":68.5,"low":66.6,"close":67.2,"volume":10164737},{"date":"2026-03-20","open":68.4,"high":68.5,"low":66.6,"close":67.2,"volume":10349545}]