[{"date":"2025-03-21","open":397,"high":399,"low":396,"close":396,"volume":12000},{"date":"2025-03-24","open":396,"high":398,"low":395,"close":397,"volume":4700},{"date":"2025-03-25","open":395,"high":397,"low":393,"close":393,"volume":16400},{"date":"2025-03-26","open":395,"high":396,"low":393,"close":396,"volume":7800},{"date":"2025-03-27","open":395,"high":395,"low":393,"close":394,"volume":3400},{"date":"2025-03-28","open":392,"high":395,"low":391,"close":393,"volume":8600},{"date":"2025-03-31","open":391,"high":393,"low":388,"close":389,"volume":21500},{"date":"2025-04-01","open":389,"high":391,"low":388,"close":389,"volume":5000},{"date":"2025-04-02","open":389,"high":390,"low":382,"close":384,"volume":23400},{"date":"2025-04-03","open":380,"high":381,"low":372,"close":372,"volume":104100},{"date":"2025-04-04","open":365,"high":365,"low":340,"close":348,"volume":53000},{"date":"2025-04-07","open":308,"high":344,"low":293,"close":308,"volume":82100},{"date":"2025-04-08","open":315,"high":333,"low":315,"close":328,"volume":19500},{"date":"2025-04-09","open":320,"high":324,"low":315,"close":318,"volume":26700},{"date":"2025-04-10","open":326,"high":355,"low":326,"close":333,"volume":19600},{"date":"2025-04-11","open":330,"high":341,"low":330,"close":341,"volume":11000},{"date":"2025-04-14","open":342,"high":345,"low":338,"close":339,"volume":8500},{"date":"2025-04-15","open":345,"high":364,"low":340,"close":357,"volume":75400},{"date":"2025-04-16","open":365,"high":393,"low":365,"close":382,"volume":85200},{"date":"2025-04-17","open":389,"high":389,"low":376,"close":387,"volume":32500},{"date":"2025-04-18","open":383,"high":399,"low":381,"close":399,"volume":24100},{"date":"2025-04-21","open":399,"high":402,"low":386,"close":396,"volume":36900},{"date":"2025-04-22","open":390,"high":400,"low":369,"close":380,"volume":100900},{"date":"2025-04-23","open":383,"high":398,"low":383,"close":396,"volume":21500},{"date":"2025-04-24","open":396,"high":398,"low":391,"close":395,"volume":5800},{"date":"2025-04-25","open":393,"high":393,"low":387,"close":389,"volume":7700},{"date":"2025-04-28","open":395,"high":397,"low":390,"close":393,"volume":4900},{"date":"2025-04-30","open":392,"high":392,"low":390,"close":390,"volume":9100},{"date":"2025-05-01","open":390,"high":390,"low":384,"close":384,"volume":12400},{"date":"2025-05-02","open":386,"high":386,"low":384,"close":385,"volume":3600},{"date":"2025-05-07","open":384,"high":385,"low":377,"close":381,"volume":4900},{"date":"2025-05-08","open":376,"high":380,"low":376,"close":376,"volume":7100},{"date":"2025-05-09","open":378,"high":380,"low":375,"close":380,"volume":9000},{"date":"2025-05-12","open":380,"high":399,"low":376,"close":384,"volume":137400},{"date":"2025-05-13","open":376,"high":383,"low":376,"close":379,"volume":14300},{"date":"2025-05-14","open":379,"high":379,"low":375,"close":377,"volume":7200},{"date":"2025-05-15","open":378,"high":378,"low":374,"close":377,"volume":8500},{"date":"2025-05-16","open":380,"high":380,"low":375,"close":380,"volume":11700},{"date":"2025-05-19","open":379,"high":380,"low":377,"close":380,"volume":15800},{"date":"2025-05-20","open":380,"high":381,"low":378,"close":378,"volume":14200},{"date":"2025-05-21","open":376,"high":386,"low":372,"close":375,"volume":57900},{"date":"2025-05-22","open":377,"high":377,"low":373,"close":376,"volume":6400},{"date":"2025-05-23","open":373,"high":378,"low":373,"close":376,"volume":3100},{"date":"2025-05-26","open":373,"high":380,"low":373,"close":379,"volume":8100},{"date":"2025-05-27","open":380,"high":382,"low":377,"close":381,"volume":5200},{"date":"2025-05-28","open":380,"high":382,"low":377,"close":382,"volume":3100},{"date":"2025-05-29","open":378,"high":382,"low":377,"close":380,"volume":5100},{"date":"2025-05-30","open":380,"high":381,"low":376,"close":380,"volume":10300},{"date":"2025-06-02","open":377,"high":381,"low":374,"close":379,"volume":33200},{"date":"2025-06-03","open":379,"high":380,"low":375,"close":378,"volume":9400},{"date":"2025-06-04","open":378,"high":380,"low":375,"close":379,"volume":9200},{"date":"2025-06-05","open":375,"high":380,"low":375,"close":380,"volume":5400},{"date":"2025-06-06","open":382,"high":382,"low":374,"close":377,"volume":7300},{"date":"2025-06-09","open":380,"high":380,"low":380,"close":380,"volume":3000},{"date":"2025-06-10","open":380,"high":394,"low":378,"close":394,"volume":51200},{"date":"2025-06-11","open":397,"high":401,"low":396,"close":400,"volume":38000},{"date":"2025-06-12","open":400,"high":414,"low":392,"close":397,"volume":66800},{"date":"2025-06-13","open":399,"high":400,"low":389,"close":400,"volume":44900},{"date":"2025-06-16","open":340,"high":358,"low":338,"close":356,"volume":259300},{"date":"2025-06-17","open":356,"high":356,"low":350,"close":356,"volume":27000},{"date":"2025-06-18","open":348,"high":354,"low":339,"close":339,"volume":96000},{"date":"2025-06-19","open":347,"high":349,"low":341,"close":345,"volume":19500},{"date":"2025-06-20","open":345,"high":352,"low":341,"close":347,"volume":31400},{"date":"2025-06-23","open":349,"high":349,"low":340,"close":341,"volume":16400},{"date":"2025-06-24","open":342,"high":343,"low":341,"close":343,"volume":27000},{"date":"2025-06-25","open":344,"high":344,"low":340,"close":341,"volume":5000},{"date":"2025-06-26","open":343,"high":349,"low":340,"close":344,"volume":16000},{"date":"2025-06-27","open":347,"high":347,"low":342,"close":345,"volume":24000},{"date":"2025-06-30","open":345,"high":346,"low":334,"close":337,"volume":94300},{"date":"2025-07-01","open":337,"high":340,"low":336,"close":336,"volume":14500},{"date":"2025-07-02","open":336,"high":338,"low":330,"close":332,"volume":20100},{"date":"2025-07-03","open":333,"high":336,"low":330,"close":332,"volume":12700},{"date":"2025-07-04","open":336,"high":336,"low":331,"close":334,"volume":8500},{"date":"2025-07-07","open":338,"high":340,"low":333,"close":333,"volume":22400},{"date":"2025-07-08","open":338,"high":357,"low":334,"close":346,"volume":38100},{"date":"2025-07-09","open":348,"high":348,"low":339,"close":344,"volume":13700},{"date":"2025-07-10","open":342,"high":343,"low":338,"close":338,"volume":14300},{"date":"2025-07-11","open":340,"high":340,"low":335,"close":339,"volume":12600},{"date":"2025-07-14","open":340,"high":341,"low":338,"close":339,"volume":13000},{"date":"2025-07-15","open":340,"high":346,"low":337,"close":339,"volume":12800},{"date":"2025-07-16","open":343,"high":345,"low":330,"close":332,"volume":43700},{"date":"2025-07-17","open":334,"high":337,"low":331,"close":332,"volume":9600},{"date":"2025-07-18","open":334,"high":339,"low":333,"close":334,"volume":6500},{"date":"2025-07-22","open":335,"high":339,"low":332,"close":339,"volume":28200},{"date":"2025-07-23","open":337,"high":345,"low":335,"close":336,"volume":58300},{"date":"2025-07-24","open":341,"high":346,"low":337,"close":346,"volume":17300},{"date":"2025-07-25","open":345,"high":346,"low":345,"close":346,"volume":15300},{"date":"2025-07-28","open":347,"high":347,"low":338,"close":339,"volume":18300},{"date":"2025-07-29","open":345,"high":345,"low":337,"close":337,"volume":11000},{"date":"2025-07-30","open":332,"high":340,"low":332,"close":334,"volume":8500},{"date":"2025-07-31","open":335,"high":347,"low":334,"close":338,"volume":20900},{"date":"2025-08-01","open":343,"high":345,"low":340,"close":345,"volume":20200},{"date":"2025-08-04","open":346,"high":346,"low":338,"close":342,"volume":21900},{"date":"2025-08-05","open":343,"high":352,"low":342,"close":347,"volume":25300},{"date":"2025-08-06","open":349,"high":350,"low":347,"close":350,"volume":15500},{"date":"2025-08-07","open":348,"high":351,"low":343,"close":348,"volume":23600},{"date":"2025-08-08","open":345,"high":345,"low":333,"close":341,"volume":49800},{"date":"2025-08-12","open":340,"high":342,"low":336,"close":338,"volume":16800},{"date":"2025-08-13","open":337,"high":339,"low":333,"close":335,"volume":48100},{"date":"2025-08-14","open":334,"high":335,"low":333,"close":335,"volume":16200},{"date":"2025-08-15","open":335,"high":338,"low":333,"close":334,"volume":29300},{"date":"2025-08-18","open":338,"high":340,"low":335,"close":337,"volume":31000},{"date":"2025-08-19","open":337,"high":350,"low":337,"close":350,"volume":29700},{"date":"2025-08-20","open":352,"high":353,"low":348,"close":348,"volume":29800},{"date":"2025-08-21","open":347,"high":364,"low":347,"close":364,"volume":46500},{"date":"2025-08-22","open":364,"high":379,"low":363,"close":379,"volume":34000},{"date":"2025-08-25","open":384,"high":430,"low":382,"close":408,"volume":302400},{"date":"2025-08-26","open":414,"high":418,"low":389,"close":397,"volume":89500},{"date":"2025-08-27","open":401,"high":401,"low":389,"close":389,"volume":36800},{"date":"2025-08-28","open":391,"high":409,"low":391,"close":402,"volume":49100},{"date":"2025-08-29","open":400,"high":400,"low":387,"close":390,"volume":42900},{"date":"2025-09-01","open":394,"high":407,"low":392,"close":407,"volume":58400},{"date":"2025-09-02","open":414,"high":414,"low":398,"close":404,"volume":28000},{"date":"2025-09-03","open":400,"high":404,"low":390,"close":390,"volume":42700},{"date":"2025-09-04","open":391,"high":398,"low":391,"close":392,"volume":31200},{"date":"2025-09-05","open":394,"high":413,"low":394,"close":405,"volume":71600},{"date":"2025-09-08","open":413,"high":413,"low":399,"close":399,"volume":37800},{"date":"2025-09-09","open":400,"high":408,"low":397,"close":406,"volume":56900},{"date":"2025-09-10","open":407,"high":425,"low":406,"close":415,"volume":109900},{"date":"2025-09-11","open":413,"high":418,"low":406,"close":412,"volume":56000},{"date":"2025-09-12","open":409,"high":420,"low":406,"close":415,"volume":103800},{"date":"2025-09-16","open":431,"high":435,"low":401,"close":409,"volume":259500},{"date":"2025-09-17","open":408,"high":418,"low":405,"close":410,"volume":113200},{"date":"2025-09-18","open":410,"high":415,"low":401,"close":412,"volume":68100},{"date":"2025-09-19","open":412,"high":412,"low":389,"close":395,"volume":98300},{"date":"2025-09-22","open":394,"high":403,"low":386,"close":393,"volume":64900},{"date":"2025-09-24","open":393,"high":393,"low":385,"close":389,"volume":22300},{"date":"2025-09-25","open":389,"high":389,"low":384,"close":386,"volume":19100},{"date":"2025-09-26","open":386,"high":466,"low":386,"close":466,"volume":166300},{"date":"2025-09-29","open":546,"high":546,"low":546,"close":546,"volume":60600},{"date":"2025-09-30","open":646,"high":646,"low":646,"close":646,"volume":28900},{"date":"2025-10-01","open":746,"high":895,"low":673,"close":699,"volume":17735300},{"date":"2025-10-02","open":799,"high":799,"low":640,"close":640,"volume":3300500},{"date":"2025-10-03","open":680,"high":740,"low":620,"close":738,"volume":3997400},{"date":"2025-10-06","open":690,"high":772,"low":640,"close":730,"volume":2028500},{"date":"2025-10-07","open":775,"high":880,"low":772,"close":880,"volume":1463100},{"date":"2025-10-08","open":920,"high":1030,"low":831,"close":1015,"volume":4760800},{"date":"2025-10-09","open":1068,"high":1290,"low":1013,"close":1252,"volume":3526800},{"date":"2025-10-10","open":1300,"high":1468,"low":1142,"close":1221,"volume":2871900},{"date":"2025-10-14","open":1165,"high":1521,"low":1152,"close":1521,"volume":3146600},{"date":"2025-10-15","open":1761,"high":1814,"low":1530,"close":1595,"volume":2961900},{"date":"2025-10-16","open":1385,"high":1490,"low":1202,"close":1309,"volume":2566500},{"date":"2025-10-17","open":1201,"high":1297,"low":1036,"close":1106,"volume":2054700},{"date":"2025-10-20","open":1100,"high":1180,"low":950,"close":992,"volume":1395000},{"date":"2025-10-21","open":982,"high":982,"low":912,"close":938,"volume":847800},{"date":"2025-10-22","open":923,"high":948,"low":877,"close":919,"volume":699900},{"date":"2025-10-23","open":960,"high":968,"low":877,"close":885,"volume":1127000},{"date":"2025-10-24","open":899,"high":929,"low":860,"close":904,"volume":935400},{"date":"2025-10-27","open":934,"high":1054,"low":920,"close":1054,"volume":1737000},{"date":"2025-10-28","open":1084,"high":1288,"low":1054,"close":1079,"volume":2743900},{"date":"2025-10-29","open":1024,"high":1216,"low":975,"close":1007,"volume":2144700},{"date":"2025-10-30","open":1000,"high":1169,"low":996,"close":1151,"volume":1764400},{"date":"2025-10-31","open":1128,"high":1130,"low":1042,"close":1059,"volume":727200},{"date":"2025-11-04","open":1089,"high":1145,"low":1018,"close":1051,"volume":646500},{"date":"2025-11-05","open":1021,"high":1073,"low":976,"close":1018,"volume":408300},{"date":"2025-11-06","open":1020,"high":1055,"low":946,"close":977,"volume":471500},{"date":"2025-11-07","open":947,"high":991,"low":884,"close":900,"volume":513700},{"date":"2025-11-10","open":913,"high":923,"low":865,"close":883,"volume":531100},{"date":"2025-11-11","open":859,"high":860,"low":770,"close":784,"volume":731000},{"date":"2025-11-12","open":785,"high":808,"low":755,"close":804,"volume":481200},{"date":"2025-11-13","open":864,"high":954,"low":861,"close":954,"volume":1075500},{"date":"2025-11-14","open":926,"high":1050,"low":902,"close":1036,"volume":2403100},{"date":"2025-11-17","open":992,"high":1104,"low":985,"close":1044,"volume":1269100},{"date":"2025-11-18","open":1000,"high":1014,"low":916,"close":954,"volume":731200},{"date":"2025-11-19","open":955,"high":972,"low":886,"close":899,"volume":420100},{"date":"2025-11-20","open":899,"high":901,"low":831,"close":861,"volume":526000},{"date":"2025-11-21","open":835,"high":865,"low":826,"close":827,"volume":330800},{"date":"2025-11-25","open":842,"high":859,"low":801,"close":817,"volume":249700},{"date":"2025-11-26","open":967,"high":967,"low":967,"close":967,"volume":46400},{"date":"2025-11-27","open":1117,"high":1117,"low":1117,"close":1117,"volume":53800},{"date":"2025-11-28","open":1325,"high":1465,"low":1194,"close":1250,"volume":6402600},{"date":"2025-12-01","open":1220,"high":1550,"low":1185,"close":1550,"volume":5553700},{"date":"2025-12-02","open":1490,"high":1494,"low":1150,"close":1150,"volume":3435600},{"date":"2025-12-03","open":1107,"high":1385,"low":1051,"close":1219,"volume":6549800},{"date":"2025-12-04","open":1166,"high":1255,"low":1137,"close":1187,"volume":1424200},{"date":"2025-12-05","open":1143,"high":1159,"low":1080,"close":1085,"volume":1118000},{"date":"2025-12-08","open":1145,"high":1180,"low":1084,"close":1100,"volume":1002100},{"date":"2025-12-09","open":1111,"high":1156,"low":1026,"close":1055,"volume":593500},{"date":"2025-12-10","open":1044,"high":1044,"low":993,"close":1008,"volume":489300},{"date":"2025-12-11","open":1016,"high":1047,"low":966,"close":973,"volume":425000},{"date":"2025-12-12","open":958,"high":1083,"low":950,"close":1042,"volume":1097900},{"date":"2025-12-15","open":939,"high":1024,"low":911,"close":993,"volume":1300700},{"date":"2025-12-16","open":1058,"high":1143,"low":1044,"close":1143,"volume":1995300},{"date":"2025-12-17","open":1095,"high":1155,"low":1005,"close":1022,"volume":1529400},{"date":"2025-12-18","open":981,"high":1185,"low":972,"close":1081,"volume":3975000},{"date":"2025-12-19","open":1071,"high":1177,"low":1031,"close":1037,"volume":1590100},{"date":"2025-12-22","open":1030,"high":1055,"low":1001,"close":1031,"volume":540900},{"date":"2025-12-23","open":1057,"high":1057,"low":1001,"close":1002,"volume":359200},{"date":"2025-12-24","open":1005,"high":1048,"low":980,"close":1021,"volume":821100},{"date":"2025-12-25","open":1020,"high":1100,"low":1005,"close":1042,"volume":848000},{"date":"2025-12-26","open":1062,"high":1070,"low":1011,"close":1015,"volume":469400},{"date":"2025-12-29","open":1005,"high":1043,"low":1005,"close":1012,"volume":392700},{"date":"2025-12-30","open":1008,"high":1017,"low":958,"close":971,"volume":551000},{"date":"2026-01-05","open":986,"high":1018,"low":956,"close":978,"volume":407100},{"date":"2026-01-06","open":999,"high":1062,"low":994,"close":1019,"volume":869800},{"date":"2026-01-07","open":1022,"high":1108,"low":1022,"close":1100,"volume":793100},{"date":"2026-01-08","open":1095,"high":1146,"low":1065,"close":1100,"volume":573300},{"date":"2026-01-09","open":1117,"high":1220,"low":1086,"close":1212,"volume":1030700},{"date":"2026-01-13","open":1215,"high":1360,"low":1215,"close":1230,"volume":1751100},{"date":"2026-01-14","open":1226,"high":1309,"low":1134,"close":1144,"volume":908400},{"date":"2026-01-15","open":1144,"high":1224,"low":1128,"close":1212,"volume":574100},{"date":"2026-01-16","open":1213,"high":1309,"low":1212,"close":1293,"volume":808000},{"date":"2026-01-19","open":1294,"high":1318,"low":1225,"close":1237,"volume":424500},{"date":"2026-01-20","open":1250,"high":1315,"low":1200,"close":1286,"volume":520800},{"date":"2026-01-21","open":1226,"high":1256,"low":1153,"close":1163,"volume":572800},{"date":"2026-01-22","open":1172,"high":1223,"low":1110,"close":1133,"volume":335700},{"date":"2026-01-23","open":1146,"high":1185,"low":1142,"close":1168,"volume":211000},{"date":"2026-01-26","open":1170,"high":1250,"low":1151,"close":1154,"volume":456100},{"date":"2026-01-27","open":1160,"high":1297,"low":1152,"close":1290,"volume":967100},{"date":"2026-01-28","open":1290,"high":1292,"low":1206,"close":1226,"volume":545700},{"date":"2026-01-29","open":1228,"high":1239,"low":1192,"close":1222,"volume":245800},{"date":"2026-01-30","open":1205,"high":1229,"low":1162,"close":1166,"volume":195200},{"date":"2026-02-02","open":1168,"high":1194,"low":1081,"close":1087,"volume":287800},{"date":"2026-02-03","open":1106,"high":1150,"low":1071,"close":1149,"volume":285700},{"date":"2026-02-04","open":1133,"high":1145,"low":1086,"close":1108,"volume":134300},{"date":"2026-02-05","open":1100,"high":1134,"low":1092,"close":1133,"volume":111800},{"date":"2026-02-06","open":1110,"high":1118,"low":1085,"close":1090,"volume":174100},{"date":"2026-02-09","open":1110,"high":1110,"low":1020,"close":1041,"volume":233400},{"date":"2026-02-10","open":1111,"high":1203,"low":1082,"close":1198,"volume":929900},{"date":"2026-02-12","open":1184,"high":1230,"low":1105,"close":1117,"volume":462900},{"date":"2026-02-13","open":1117,"high":1118,"low":1070,"close":1077,"volume":163100},{"date":"2026-02-16","open":1100,"high":1150,"low":1100,"close":1150,"volume":328400},{"date":"2026-02-17","open":1158,"high":1158,"low":1102,"close":1142,"volume":203200},{"date":"2026-02-18","open":1125,"high":1182,"low":1124,"close":1169,"volume":156500},{"date":"2026-02-19","open":1289,"high":1375,"low":1275,"close":1364,"volume":2367900},{"date":"2026-02-20","open":1320,"high":1363,"low":1230,"close":1274,"volume":828200},{"date":"2026-02-24","open":1260,"high":1261,"low":1185,"close":1213,"volume":326400},{"date":"2026-02-25","open":1232,"high":1236,"low":1190,"close":1213,"volume":195300},{"date":"2026-02-26","open":1214,"high":1215,"low":1168,"close":1181,"volume":280800},{"date":"2026-02-27","open":1188,"high":1240,"low":1170,"close":1234,"volume":229200},{"date":"2026-03-02","open":1175,"high":1185,"low":1121,"close":1145,"volume":451300},{"date":"2026-03-03","open":1175,"high":1178,"low":1095,"close":1095,"volume":262400},{"date":"2026-03-04","open":1050,"high":1072,"low":973,"close":993,"volume":513000},{"date":"2026-03-05","open":1038,"high":1118,"low":1038,"close":1085,"volume":360800},{"date":"2026-03-06","open":1070,"high":1090,"low":1050,"close":1081,"volume":119300},{"date":"2026-03-09","open":1007,"high":1036,"low":989,"close":1015,"volume":218900},{"date":"2026-03-10","open":1040,"high":1071,"low":1026,"close":1071,"volume":151800},{"date":"2026-03-11","open":1085,"high":1134,"low":1080,"close":1110,"volume":251000},{"date":"2026-03-12","open":1100,"high":1128,"low":1084,"close":1086,"volume":200100},{"date":"2026-03-13","open":1056,"high":1125,"low":1052,"close":1125,"volume":174000},{"date":"2026-03-16","open":1104,"high":1134,"low":1096,"close":1100,"volume":211700},{"date":"2026-03-17","open":965,"high":973,"low":934,"close":941,"volume":600700},{"date":"2026-03-18","open":926,"high":934,"low":870,"close":880,"volume":489100},{"date":"2026-03-19","open":888,"high":895,"low":870,"close":876,"volume":208100},{"date":"2026-03-19","open":888,"high":895,"low":870,"close":876,"volume":208100}]